testpackagegepmc/__init__.py
testpackagegepmc/jsonresponse.py
testpackagegepmc/queryentities.py
testpackagegepmc-0.0.4.dist-info/METADATA
testpackagegepmc-0.0.4.dist-info/WHEEL
testpackagegepmc-0.0.4.dist-info/top_level.txt
testpackagegepmc-0.0.4.dist-info/RECORD
